MANIFEST.in
README.rst
setup.py
iampharaoh/__init__.py
iampharaoh.egg-info/PKG-INFO
iampharaoh.egg-info/SOURCES.txt
iampharaoh.egg-info/dependency_links.txt
iampharaoh.egg-info/entry_points.txt
iampharaoh.egg-info/not-zip-safe
iampharaoh.egg-info/requires.txt
iampharaoh.egg-info/top_level.txt
iampharaoh/app/__init__.py_tmpl
iampharaoh/app/forms.py_tmpl
iampharaoh/app/models.py_tmpl
iampharaoh/app/urls.py_tmpl
iampharaoh/app/views.py_tmpl
iampharaoh/app/templates/index.html_tmpl
iampharaoh/project/LICENSE_tmpl
iampharaoh/project/MANIFEST.in_tmpl
iampharaoh/project/README.md_tmpl
iampharaoh/project/development.ini_tmpl
iampharaoh/project/production.ini_tmpl
iampharaoh/project/setup.cfg_tmpl
iampharaoh/project/setup.py_tmpl
iampharaoh/project/+package+/__init__.py_tmpl
iampharaoh/project/+package+/+project+/__init__.py_tmpl
iampharaoh/project/+package+/+project+/base_model.py
iampharaoh/project/+package+/+project+/urls.py_tmpl
iampharaoh/project/+package+/scripts/__init__.py
iampharaoh/project/+package+/scripts/destroydb.py_tmpl
iampharaoh/project/+package+/scripts/initializedb.py_tmpl
iampharaoh/project/+package+/static/style.css