Metadata-Version: 1.1
Name: iampharaoh
Version: 0.0.2
Summary: A Pyramid Scaffold to Pony users (django) by Mario Idival
Home-page: https://github.com/marioidival/iampharaoh
Author: Mario Idival
Author-email: marioidival@gmail.com
License: UNKNOWN
Keywords: pyramid scaffold
Platform: UNKNOWN
Classifier: Programming Language :: Python
Classifier: Framework :: Pyramid
Classifier: Topic :: Internet :: WWW/HTTP
Classifier: Topic :: Internet :: WWW/HTTP :: WSGI :: Application
